<dir>
    <title>urban actor</title>
    <link>https://raw.githubusercontent.com/lost50/timber/master/Urban%20actors.xml</link>
</dir>
<dir>
    <title>actors (2)</title>
    <link>https://raw.githubusercontent.com/lost50/timber/master/actors%20(2).xml</link>
  </dir>
<dir>
    <title>actress</title>
    <link>https://raw.githubusercontent.com/lost50/timber/master/actress.xml</link>
</dir>
<dir>
    <title>actors</title>
    <link>https://raw.githubusercontent.com/lost50/timber/master/actors.xml</link>
</dir>