<dir>
      <title>TMDB Upcoming</title>
      <tmdb>movie/upcoming</tmdb>
      <summary>Shows Trailers For Upcoming Movies</summary>
</dir>

<dir>
      <title>TMDB Now Playing</title>
      <tmdb>movies/now_playing</tmdb>
</dir>
  
<dir>
<title>Movie Years</title>
<link>https://raw.githubusercontent.com/Trapper69/trappor/master/tmdbyear2.xml</link>
</dir>
 <dir>
        <title>action thriller movies 2017</title>
        <tmdb>list/63866</tmdb>
        <thumbnail></thumbnail>
        <fanart></fanart>
</dir> 

<dir>
        <title>New Movies</title>
        <tmdb>list/97791</tmdb>
        <thumbnail></thumbnail>
        <fanart></fanart>
</dir> 
<dir>
        <title>animated movies</title>
        <tmdb>list/97709</tmdb>
        <thumbnail></thumbnail>
        <fanart></fanart>
</dir> 

<dir>
        <title>GIRLS WITH GUNS</title>
        <tmdb>list/93</tmdb>
        <thumbnail></thumbnail>
        <fanart></fanart>
</dir> 

<dir>
        <title>dc Movies</title>
        <tmdb>list/3</tmdb>
        <thumbnail></thumbnail>
        <fanart></fanart>
</dir> 

<dir>
        <title>Science ficition flicks</title>
        <tmdb>list/3945</tmdb>
        <thumbnail></thumbnail>
        <fanart></fanart>
</dir> 
<dir>
        <title>Assassin</title>
        <tmdb>list/63741</tmdb>
        <thumbnail></thumbnail>
        <fanart></fanart>
</dir> 
<dir>
        <title>Dragon Ball</title>
        <tmdb>list/78499</tmdb>
        <thumbnail></thumbnail>
        <fanart></fanart>
</dir> 
<dir>
        <title>Boxing</title>
        <tmdb>list/63100</tmdb>
        <thumbnail></thumbnail>
        <fanart></fanart>
</dir> 
<dir>
        <title>special forces</title>
        <tmdb>list/65096</tmdb>
        <thumbnail></thumbnail>
        <fanart></fanart>
</dir> 
<dir>
        <title>DC/Marvel</title>
        <tmdb>list/3945</tmdb>
        <thumbnail></thumbnail>
        <fanart></fanart>
</dir> 
<dir>
        <title>Hood</title>
        <tmdb>list/50624</tmdb>
        <thumbnail></thumbnail>
        <fanart></fanart>
</dir>
   
<dir>
   <title>Fighing </title>
   <link>https://raw.githubusercontent.com/jay6912/trap/master/t%20fight.xml</link>
</dir>
<dir>
        <title>mythology</title>
        <tmdb>https://www.themoviedb.org/list/47717</tmdb>
        <thumbnail></thumbnail>
        <fanart></fanart>
</dir>
 <dir>
        <title>Hood Movies</title>
        <tmdb>https://www.themoviedb.org/list/50624</tmdb>
        <thumbnail></thumbnail>
        <fanart></fanart>
</dir>
  <dir>
        <title>westerns</title>
        <tmdb>https://www.themoviedb.org/list/47711</tmdb>
        <thumbnail></thumbnail>
        <fanart></fanart>
</dir>
 <dir>
        <title>Greek and Roman movies</title>
        <tmdb>https://www.themoviedb.org/list/63883</tmdb>
        <thumbnail></thumbnail>
        <fanart></fanart>
</dir>
   <dir>
        <title>Tyler Perry movies</title>
        <tmdb>https://www.themoviedb.org/list/48265</tmdb>
        <thumbnail></thumbnail>
        <fanart></fanart>
</dir>
 <dir>
        <title>Comedy</title>
        <tmdb>https://www.themoviedb.org/list/47754</tmdb>
        <thumbnail></thumbnail>
        <fanart></fanart>
</dir>
  
